lionspeed/__init__.py
lionspeed/ml.py
lionspeed-0.0.1.dist-info/LICENSE
lionspeed-0.0.1.dist-info/METADATA
lionspeed-0.0.1.dist-info/WHEEL
lionspeed-0.0.1.dist-info/top_level.txt
lionspeed-0.0.1.dist-info/RECORD
