Metadata-Version: 2.1
Name: lionspeed
Version: 0.0.1
Summary: A small package that contains all the source code of deep learning practicles
Author: vedant
Author-email: vedantnikam798@gmail.com
Classifier: Programming Language :: Python :: 3
Classifier: License :: OSI Approved :: MIT License
Classifier: Operating System :: OS Independent
Requires-Python: >=3.6
License-File: LICENSE
